opencnpj/__init__.py
opencnpj/exceptions.py
opencnpj/opencnpj.py
opencnpj/utils.py
python_opencnpj-0.1.4.dist-info/licenses/LICENSE
python_opencnpj-0.1.4.dist-info/METADATA
python_opencnpj-0.1.4.dist-info/WHEEL
python_opencnpj-0.1.4.dist-info/top_level.txt
python_opencnpj-0.1.4.dist-info/RECORD
