Metadata-Version: 2.4
Name: python-opencnpj
Version: 0.1.4
Summary: Python library to fetch CNPJ data from OpenCNPJ API
Author-email: Gustavo Gomes Nogueira da Silva <gustavogonosi@gmail.com>
Project-URL: Repository, https://github.com/gustavogomesn/python-opencnpj
Requires-Python: >=3.11
License-File: LICENSE
Requires-Dist: requests>=2.32
Requires-Dist: urllib3
Dynamic: license-file
